<?xml version="1.0" encoding="UTF-8"?>
<!DOCTYPE config SYSTEM "reggateconfigmap.dtd">
<config>
	<param name='check_name'>N</param>
	<param name='conn_timeout'>5</param>
	<param name='read_timeout'>10</param>
	<param name='migrate_read_timeout'>13</param>
	<param name='cache_refresh_rate'>5</param>
        <param name='alpo_partner'>ycorp</param>
        <param name='alpo_webservice'>http://hostname/extacct/v1/</param>
        <param name='appid'>yahoo.mail.reggate.xset.deploy-stage3</param>
      </config>
